afsmon/__init__.py
afsmon/cmd/__init__.py
afsmon/cmd/main.py
afsmon/tests/__init__.py
afsmon/tests/base.py
afsmon/tests/test_afsmon.py
afsmon/tests/fixtures/vos-listvol.txt
afsmon-1.2.0.dist-info/AUTHORS
afsmon-1.2.0.dist-info/LICENSE
afsmon-1.2.0.dist-info/METADATA
afsmon-1.2.0.dist-info/WHEEL
afsmon-1.2.0.dist-info/entry_points.txt
afsmon-1.2.0.dist-info/pbr.json
afsmon-1.2.0.dist-info/top_level.txt
afsmon-1.2.0.dist-info/RECORD
