Metadata-Version: 2.1
Name: afsmon
Version: 1.2.0
Summary: Helpers for AFS monitoring in Python
Home-page: https://github.com/ianw/pyafsmon
Author: Ian Wienand
Author-email: ian@wienand.org
License: UNKNOWN
Platform: UNKNOWN
Classifier: Intended Audience :: Information Technology
Classifier: Intended Audience :: System Administrators
Classifier: License :: OSI Approved :: Apache Software License
Classifier: Operating System :: POSIX :: Linux
Classifier: Programming Language :: Python :: 3
Classifier: Programming Language :: Python :: 3.3
Classifier: Programming Language :: Python :: 3.4
Classifier: Programming Language :: Python :: 3.5
Classifier: Programming Language :: Python :: 3.6
Requires-Dist: pbr (!=2.1.0,>=2.0.0)
Requires-Dist: PrettyTable (<0.8)
Requires-Dist: statsd (>=3.2.1)
